oh_my_bloom/__init__.py
oh_my_bloom/datamodule.py
oh_my_bloom/model.py
oh_my_bloom/tokenizer.py
oh_my_bloom-0.1.0.dist-info/LICENSE
oh_my_bloom-0.1.0.dist-info/WHEEL
oh_my_bloom-0.1.0.dist-info/METADATA
oh_my_bloom-0.1.0.dist-info/RECORD
