Metadata-Version: 2.1
Name: oh-my-bloom
Version: 0.1.0
Summary: 中文BLOOM语言模型
License: MIT
Author: 善若水
Author-email: 790990241@qq.com
Requires-Python: >=3.9,<4.0
Classifier: License :: OSI Approved :: MIT License
Classifier: Programming Language :: Python :: 3
Classifier: Programming Language :: Python :: 3.9
Classifier: Programming Language :: Python :: 3.10
Classifier: Programming Language :: Python :: 3.11
Requires-Dist: deepspeed (>=0.9.0)
Requires-Dist: lightning (>=2.0.1)
Requires-Dist: transformers (>=4.27.1)
Requires-Dist: wandb (>=0.14.2)
